ra3map/__init__.py
ra3map/ra3map.py
ra3map/enums/__init__.py
ra3map/enums/passability_enum.py
ra3map/enums/texture_enum.py
ra3map/lib/MapCoreLibMod.dll
ra3map/lib/Newtonsoft.Json.dll
ra3map/lib/Ra3MapBridge.dll
ra3map/lib/System.CodeDom.dll
ra3map/lib/System.Drawing.Common.dll
ra3map/models/__init__.py
ra3map/models/object_model.py
ra3map/models/player_model.py
ra3map/models/team_model.py
ra3map/models/waypoint_model.py
ra3map-1.0.3.dist-info/licenses/LICENSE
ra3map-1.0.3.dist-info/METADATA
ra3map-1.0.3.dist-info/WHEEL
ra3map-1.0.3.dist-info/top_level.txt
ra3map-1.0.3.dist-info/RECORD
