Metadata-Version: 2.4
Name: ra3map
Version: 1.0.3
Summary: a operator for ra3 map
Author-email: dreamness <dnalm.dreamness@gmail.com>
License: MIT
Project-URL: Homepage, https://github.com/dreamness-dnalm/ra3map_python
Project-URL: Documentation, https://github.com/dreamness-dnalm/ra3map_python/wiki
Project-URL: Repository, https://github.com/dreamness-dnalm/ra3map_python
Project-URL: Issues, https://github.com/dreamness-dnalm/ra3map_python/issues
Requires-Python: >=3.5
License-File: LICENSE
Requires-Dist: pythonnet>=3.0.5
Dynamic: license-file
